cvpack/__init__.py
cvpack/cvtypes.py
cvpack/extras/__init__.py
cvpack/extras/clustering.py
cvpack/extras/imgproc.py
cvpack/extras/iterators.py
cvpack/extras/matlab.py
cvpack/imgio.py
cvpack/py.typed
cvpack/videoio.py
cvpack_alkasm-1.1.0.dist-info/LICENSE
cvpack_alkasm-1.1.0.dist-info/WHEEL
cvpack_alkasm-1.1.0.dist-info/METADATA
cvpack_alkasm-1.1.0.dist-info/RECORD
